pawcli/__init__.py
pawcli/__main__.py
pawcli/app.py
pawcli/py.typed
pawcli/version.py
pawcli/commands/__init__.py
pawcli/commands/console.py
pawcli/commands/file.py
pawcli/commands/students.py
pawcli/commands/system.py
pawcli/commands/task/__init__.py
pawcli/commands/task/alwayson.py
pawcli/commands/task/params.py
pawcli/commands/task/scheduled.py
pawcli/commands/webapp/__init__.py
pawcli/commands/webapp/app.py
pawcli/commands/webapp/header.py
pawcli/commands/webapp/params.py
pawcli/commands/webapp/ssl.py
pawcli/commands/webapp/static.py
pawcli/core/__init__.py
pawcli/core/callback.py
pawcli/core/config.py
pawcli/core/context.py
pawcli/core/enum.py
pawcli/core/formatter.py
pawcli/core/path.py
pawcli/core/result.py
pawcli/core/utils.py
pypawcli-1.1.0.dist-info/METADATA
pypawcli-1.1.0.dist-info/WHEEL
pypawcli-1.1.0.dist-info/entry_points.txt
pypawcli-1.1.0.dist-info/licenses/LICENSE
pypawcli-1.1.0.dist-info/RECORD
