Metadata-Version: 2.1
Name: pypawcli
Version: 1.1.0
Summary: CLI tool for PythonAnywhere
Project-URL: Source, https://codeberg.org/maraudeur/pawcli
Author-email: Maraudeur <maraudeur1@protonmail.ch>
License:  The MIT License (MIT)
License-File: LICENSE
Keywords: cli,pawcli,pythonanywhere
Classifier: License :: OSI Approved :: MIT License
Classifier: Programming Language :: Python
Classifier: Programming Language :: Python :: 3
Classifier: Programming Language :: Python :: 3 :: Only
Classifier: Programming Language :: Python :: 3.7
Classifier: Programming Language :: Python :: 3.8
Classifier: Programming Language :: Python :: 3.9
Classifier: Programming Language :: Python :: 3.10
Classifier: Programming Language :: Python :: 3.11
Requires-Python: >=3.7
Requires-Dist: pypawapi<3.0.0,>=2.0.0
Requires-Dist: typer<1.0.0,>=0.6.1
Provides-Extra: dev
Requires-Dist: pre-commit<3.0.0,>=2.0.0; extra == 'dev'
Provides-Extra: lint
Requires-Dist: flake8-bugbear==22.6.22; extra == 'lint'
Requires-Dist: flake8==5.0.4; extra == 'lint'
Requires-Dist: isort<6.0.0,>=5.10.1; extra == 'lint'
Requires-Dist: toml==0.10.2; extra == 'lint'
Requires-Dist: yapf==0.32.0; extra == 'lint'
Provides-Extra: test
Requires-Dist: coverage<7.0.0,>=6.0.0; extra == 'test'
Requires-Dist: pytest-cov<4.0.0,>=3.0.0; extra == 'test'
Requires-Dist: pytest<7.0.0,>=6.0.0; extra == 'test'
